LICENSE
MANIFEST.in
README.rst
requirements.txt
setup.py
text.log
atcy/__init__.py
atcy.egg-info/PKG-INFO
atcy.egg-info/SOURCES.txt
atcy.egg-info/dependency_links.txt
atcy.egg-info/top_level.txt
atcy/Package_A/Model_A1.py
atcy/Package_A/Model_A2.py
atcy/Package_A/Model_A3.py
atcy/Package_A/__init__.py
atcy/Package_A/ff.py
atcy/Package_B/Model_B1.py
atcy/Package_B/__init__.py