Metadata-Version: 2.1
Name: atcy
Version: 0.2.0
Summary: A small example package测试包
Home-page: https://github.com/pypa/sampleproject
Author: Tcy
Author-email: 979442421@qq.com
License: UNKNOWN
Keywords: atcy,Package_A1
Platform: UNKNOWN
Classifier: Programming Language :: Python :: 3
Classifier: License :: OSI Approved :: MIT License
Classifier: Operating System :: Microsoft :: Windows
